doc_to_md/__init__.py
doc_to_md/_version.py
doc_to_md/doc_to_md.py
doc_to_readme-1.2.0.dist-info/LICENSE
doc_to_readme-1.2.0.dist-info/METADATA
doc_to_readme-1.2.0.dist-info/WHEEL
doc_to_readme-1.2.0.dist-info/top_level.txt
doc_to_readme-1.2.0.dist-info/RECORD
