Metadata-Version: 2.1
Name: doc-to-readme
Version: 1.2.0
Summary: Automated Python Module Documentation in Markdown File (README)
Author-email: Mirjam Ziselsberger <ziselsberger@gmail.com>
License: MIT License
Project-URL: Homepage, https://github.com/ziselsberger/doc_to_readme
Project-URL: Bug Tracker, https://github.com/ziselsberger/doc_to_readme/issues
Classifier: Programming Language :: Python :: 3
Classifier: License :: OSI Approved :: MIT License
Classifier: Operating System :: OS Independent
Requires-Python: >=3.8
License-File: LICENSE
